{"v":5,"entries":{"components-odontogram--light":{"type":"story","subtype":"story","id":"components-odontogram--light","name":"Light","title":"Components/Odontogram","importPath":"./src/stories/Example.stories.tsx","componentPath":"./src/index.ts","tags":["dev","test","manifest"],"exportName":"Light"},"components-odontogram--dark":{"type":"story","subtype":"story","id":"components-odontogram--dark","name":"Dark","title":"Components/Odontogram","importPath":"./src/stories/Example.stories.tsx","componentPath":"./src/index.ts","tags":["dev","test","manifest"],"exportName":"Dark"},"components-odontogram--default":{"type":"story","subtype":"story","id":"components-odontogram--default","name":"Default","title":"Components/Odontogram","importPath":"./src/stories/Example.stories.tsx","componentPath":"./src/index.ts","tags":["dev","test","manifest"],"exportName":"Default"},"components-odontogram--with-custom-tooltip":{"type":"story","subtype":"story","id":"components-odontogram--with-custom-tooltip","name":"Custom Tooltip","title":"Components/Odontogram","importPath":"./src/stories/Example.stories.tsx","componentPath":"./src/index.ts","tags":["dev","test","manifest"],"exportName":"WithCustomTooltip"},"components-odontogram--without-tooltip":{"type":"story","subtype":"story","id":"components-odontogram--without-tooltip","name":"Without Tooltip","title":"Components/Odontogram","importPath":"./src/stories/Example.stories.tsx","componentPath":"./src/index.ts","tags":["dev","test","manifest"],"exportName":"WithoutTooltip"},"components-odontogram--upper-half":{"type":"story","subtype":"story","id":"components-odontogram--upper-half","name":"UpperHalf","title":"Components/Odontogram","importPath":"./src/stories/Example.stories.tsx","componentPath":"./src/index.ts","tags":["dev","test","manifest"],"exportName":"UpperHalf"},"components-odontogram--lower-half":{"type":"story","subtype":"story","id":"components-odontogram--lower-half","name":"LowerHalf","title":"Components/Odontogram","importPath":"./src/stories/Example.stories.tsx","componentPath":"./src/index.ts","tags":["dev","test","manifest"],"exportName":"LowerHalf"},"components-form--form":{"type":"story","subtype":"story","id":"components-form--form","name":"Form","title":"Components/Form","importPath":"./src/stories/Form.stories.tsx","componentPath":"./src/index.ts","tags":["dev","test","manifest"],"exportName":"Form"},"components-form--pure-uncontrolled-form":{"type":"story","subtype":"story","id":"components-form--pure-uncontrolled-form","name":"Pure Uncontrolled Form","title":"Components/Form","importPath":"./src/stories/Form.stories.tsx","componentPath":"./src/index.ts","tags":["dev","test","manifest"],"exportName":"PureUncontrolledForm"},"components-baby-teeth--form":{"type":"story","subtype":"story","id":"components-baby-teeth--form","name":"Form","title":"Components/Baby Teeth ","importPath":"./src/stories/zBaby.stories.tsx","componentPath":"./src/index.ts","tags":["dev","test","manifest"],"exportName":"Form"},"components-baby-teeth--pure-uncontrolled-form":{"type":"story","subtype":"story","id":"components-baby-teeth--pure-uncontrolled-form","name":"Pure Uncontrolled Form","title":"Components/Baby Teeth ","importPath":"./src/stories/zBaby.stories.tsx","componentPath":"./src/index.ts","tags":["dev","test","manifest"],"exportName":"PureUncontrolledForm"}}}